{
  "_comment": "Add your affiliate links here. Keys are matched case-insensitively against the product name on the line preceding each [AFFILIATE LINK] placeholder.",
  "mailchimp": "https://YOUR_AFFILIATE_LINK/mailchimp",
  "mailerlite": "https://www.mailerlite.com/?linkId=lp_170762&sourceId=agenticreviews&tenantId=mailerlite",
  "brevo": "https://YOUR_AFFILIATE_LINK/brevo",
  "monday": "https://YOUR_AFFILIATE_LINK/monday",
  "monday.com": "https://YOUR_AFFILIATE_LINK/monday",
  "calendly": "https://YOUR_AFFILIATE_LINK/calendly",
  "acuity": "https://YOUR_AFFILIATE_LINK/acuity",
  "acuity scheduling": "https://YOUR_AFFILIATE_LINK/acuity",
  "tidycal": "https://YOUR_AFFILIATE_LINK/tidycal"
}
